README.md
setup.py
obplib/AcceleratingCurve.py
obplib/AcceleratingLine.py
obplib/Beamparameters.py
obplib/Curve.py
obplib/FileHandler.py
obplib/Line.py
obplib/OBP.proto
obplib/PacketHandler.py
obplib/PathSegment.py
obplib/Point.py
obplib/SyncPoint.py
obplib/TimedPoints.py
obplib/Transformations.py
obplib/Vector.py
obplib/__init__.py
obplib/_version.py
obplib.egg-info/PKG-INFO
obplib.egg-info/SOURCES.txt
obplib.egg-info/dependency_links.txt
obplib.egg-info/entry_points.txt
obplib.egg-info/requires.txt
obplib.egg-info/top_level.txt
obplib/compiler/__init__.py
obplib/compiler/__main__.py
obplib/compiler/segment_handler.py
obplib/compiler/svg2obp.py
obplib/viewer/__init__.py
obplib/viewer/notebook_viewer.py
obplib/viewer/obpviewer.py