Metadata-Version: 2.1
Name: obplib
Version: 3.0.5
Summary: A library for the creation of beam paths
Home-page: https://gitlab.com/freemelt/openmelt/obplib-python
Download-URL: https://gitlab.com/freemelt/openmelt/obplib-python/-/archive/0.3.0/obplib-python-0.3.0.tar.gz
Author: Freemelt AB
Author-email: opensource@freemelt.com
License: apache-2.0
Keywords: obp openbeampath freemelt
Classifier: Development Status :: 3 - Alpha
Classifier: Intended Audience :: Developers
Classifier: Programming Language :: Python :: 3
Classifier: License :: OSI Approved :: Apache Software License
Classifier: Operating System :: OS Independent
